{
    "success": true,
    "message": "Get list address success!",
    "data": [
        {
            "id": 433047,
            "name": "Phia Trang",
            "pid": 14898,
            "type": 16,
            "region": null,
            "alias": "phia trang",
            "is_picked": "",
            "is_delivered": 1,
            "lat": "22.4933358",
            "lng": "105.35995679999996"
        },
        {
            "id": 613881,
            "name": "Thôn Bản Dạ",
            "pid": 14898,
            "type": 16,
            "region": null,
            "alias": "Thôn Bản Dạ",
            "is_picked": "",
            "is_delivered": 1,
            "lat": "22.4933358",
            "lng": "105.35995679999996"
        },
        {
            "id": 613884,
            "name": "Thôn Bản Lằn",
            "pid": 14898,
            "type": 16,
            "region": null,
            "alias": "Thôn Bản Lằn",
            "is_picked": "",
            "is_delivered": 1,
            "lat": "22.4933358",
            "lng": "105.35995679999996"
        },
        {
            "id": 613887,
            "name": "Thôn Bản Tàm",
            "pid": 14898,
            "type": 16,
            "region": null,
            "alias": "Thôn Bản Tàm",
            "is_picked": "",
            "is_delivered": 1,
            "lat": "22.4933358",
            "lng": "105.35995679999996"
        },
        {
            "id": 613866,
            "name": "Thôn Nà Cọn",
            "pid": 14898,
            "type": 16,
            "region": null,
            "alias": "Thôn Nà Cọn",
            "is_picked": "",
            "is_delivered": 1,
            "lat": "22.4933358",
            "lng": "105.35995679999996"
        },
        {
            "id": 613863,
            "name": "Thôn Nà Lạ",
            "pid": 14898,
            "type": 16,
            "region": null,
            "alias": "Thôn Nà Lạ",
            "is_picked": "",
            "is_delivered": 1,
            "lat": "22.4933358",
            "lng": "105.35995679999996"
        },
        {
            "id": 613872,
            "name": "Thôn Nà Mu",
            "pid": 14898,
            "type": 16,
            "region": null,
            "alias": "Thôn Nà Mu",
            "is_picked": "",
            "is_delivered": 1,
            "lat": "22.4933358",
            "lng": "105.35995679999996"
        },
        {
            "id": 613890,
            "name": "Thôn Nà Sảm",
            "pid": 14898,
            "type": 16,
            "region": null,
            "alias": "Thôn Nà Sảm",
            "is_picked": "",
            "is_delivered": 1,
            "lat": "22.4933358",
            "lng": "105.35995679999996"
        },
        {
            "id": 613860,
            "name": "Thôn Pắc Hẩu",
            "pid": 14898,
            "type": 16,
            "region": null,
            "alias": "Thôn Pắc Hẩu",
            "is_picked": "",
            "is_delivered": 1,
            "lat": "22.4933358",
            "lng": "105.35995679999996"
        },
        {
            "id": 613869,
            "name": "Thôn Phia Trang",
            "pid": 14898,
            "type": 16,
            "region": null,
            "alias": "Thôn Phia Trang",
            "is_picked": "",
            "is_delivered": 1,
            "lat": "22.4933358",
            "lng": "105.35995679999996"
        },
        {
            "id": 433051,
            "name": "Thôn Thuông Kiệu",
            "pid": 14898,
            "type": 16,
            "region": null,
            "alias": "thôn thuông kiệu",
            "is_picked": "",
            "is_delivered": 1,
            "lat": "22.4933358",
            "lng": "105.35995679999996"
        },
        {
            "id": 613875,
            "name": "Thôn Thuông Kiệu",
            "pid": 14898,
            "type": 16,
            "region": null,
            "alias": "Thôn Thuông Kiệu",
            "is_picked": "",
            "is_delivered": 1,
            "lat": "22.4933358",
            "lng": "105.35995679999996"
        },
        {
            "id": 433053,
            "name": "Thôn Vàng Bo",
            "pid": 14898,
            "type": 16,
            "region": null,
            "alias": "thôn vàng bo",
            "is_picked": "",
            "is_delivered": 1,
            "lat": "22.4933358",
            "lng": "105.35995679999996"
        },
        {
            "id": 613878,
            "name": "Thôn Vàng Bo",
            "pid": 14898,
            "type": 16,
            "region": null,
            "alias": "Thôn Vàng Bo",
            "is_picked": "",
            "is_delivered": 1,
            "lat": "22.4933358",
            "lng": "105.35995679999996"
        }
    ],
    "log_id": "6758138a66f75809"
}