{
    "success": true,
    "message": "Get list address success!",
    "data": [
        {
            "id": 792688,
            "name": "Bệnh Viện Y Học Cổ Truyền",
            "pid": 15101,
            "type": 6,
            "region": null,
            "alias": "Bệnh Viện Y Học Cổ Truyền",
            "is_picked": 1,
            "is_delivered": 1,
            "lat": "10.9383013",
            "lng": "108.11138040000004"
        },
        {
            "id": 798949,
            "name": "Đại Lộ Hùng Vương",
            "pid": 15101,
            "type": 21,
            "region": null,
            "alias": "Đại Lộ Hùng Vương",
            "is_picked": "",
            "is_delivered": 1,
            "lat": "10.9383013",
            "lng": "108.11138040000003"
        },
        {
            "id": 996425,
            "name": "Đặng Thai Mai",
            "pid": 15101,
            "type": 21,
            "region": null,
            "alias": "Đặng Thai Mai",
            "is_picked": 1,
            "is_delivered": 1,
            "lat": "10.9383013",
            "lng": "108.11138040000004"
        },
        {
            "id": 991121,
            "name": "Đường 308-408 Thủ Khoa Huân",
            "pid": 15101,
            "type": 21,
            "region": null,
            "alias": "Đường 308-408 Thủ Khoa Huân",
            "is_picked": "",
            "is_delivered": 1,
            "lat": "10.9383013",
            "lng": "108.11138040000003"
        },
        {
            "id": 991122,
            "name": "Đường 351-443 Thủ Khoa Huân",
            "pid": 15101,
            "type": 21,
            "region": null,
            "alias": "Đường 351-443 Thủ Khoa Huân",
            "is_picked": "",
            "is_delivered": 1,
            "lat": "10.9383013",
            "lng": "108.11138040000003"
        },
        {
            "id": 568641,
            "name": "Đường Bùi Viện",
            "pid": 15101,
            "type": 21,
            "region": null,
            "alias": "Đường Bùi Viện",
            "is_picked": 1,
            "is_delivered": 1,
            "lat": "10.9383013",
            "lng": "108.11138040000003"
        },
        {
            "id": 568728,
            "name": "Đường Cà Chua",
            "pid": 15101,
            "type": 21,
            "region": null,
            "alias": "Đường Cà Chua",
            "is_picked": "",
            "is_delivered": 1,
            "lat": "10.9383013",
            "lng": "108.11138040000003"
        },
        {
            "id": 568635,
            "name": "Đường Châu Văn Liêm",
            "pid": 15101,
            "type": 21,
            "region": null,
            "alias": "Đường Châu Văn Liêm",
            "is_picked": 1,
            "is_delivered": 1,
            "lat": "10.9383013",
            "lng": "108.11138040000003"
        },
        {
            "id": 568617,
            "name": "Đường Đặng Tất",
            "pid": 15101,
            "type": 21,
            "region": null,
            "alias": "Đường Đặng Tất",
            "is_picked": 1,
            "is_delivered": 1,
            "lat": "10.9383013",
            "lng": "108.11138040000003"
        },
        {
            "id": 568725,
            "name": "Đường Đặng Thanh Mai",
            "pid": 15101,
            "type": 21,
            "region": null,
            "alias": "Đường Đặng Thanh Mai",
            "is_picked": "",
            "is_delivered": 1,
            "lat": "10.9383013",
            "lng": "108.11138040000003"
        },
        {
            "id": 568578,
            "name": "Đường Đặng Thị Nhu",
            "pid": 15101,
            "type": 21,
            "region": null,
            "alias": "Đường Đặng Thị Nhu",
            "is_picked": 1,
            "is_delivered": 1,
            "lat": "10.9383013",
            "lng": "108.11138040000003"
        },
        {
            "id": 568716,
            "name": "Đường Đào Duy Tùng",
            "pid": 15101,
            "type": 21,
            "region": null,
            "alias": "Đường Đào Duy Tùng",
            "is_picked": "",
            "is_delivered": 1,
            "lat": "10.9383013",
            "lng": "108.11138040000003"
        },
        {
            "id": 568734,
            "name": "Đường Đào Tấn",
            "pid": 15101,
            "type": 21,
            "region": null,
            "alias": "Đường Đào Tấn",
            "is_picked": "",
            "is_delivered": 1,
            "lat": "10.9383013",
            "lng": "108.11138040000003"
        },
        {
            "id": 991123,
            "name": "Đường Dốc Văn Công",
            "pid": 15101,
            "type": 21,
            "region": null,
            "alias": "Đường Dốc Văn Công",
            "is_picked": "",
            "is_delivered": 1,
            "lat": "10.935530300000002",
            "lng": "108.13249059999998"
        },
        {
            "id": 568680,
            "name": "Đường Đỗ Hành",
            "pid": 15101,
            "type": 21,
            "region": null,
            "alias": "Đường Đỗ Hành",
            "is_picked": "",
            "is_delivered": 1,
            "lat": "10.9383013",
            "lng": "108.11138040000003"
        },
        {
            "id": 568638,
            "name": "Đường Dương Đình Nghệ",
            "pid": 15101,
            "type": 21,
            "region": null,
            "alias": "Đường Dương Đình Nghệ",
            "is_picked": 1,
            "is_delivered": 1,
            "lat": "10.9383013",
            "lng": "108.11138040000003"
        },
        {
            "id": 568719,
            "name": "Đường Hoàng Bích Sơn",
            "pid": 15101,
            "type": 21,
            "region": null,
            "alias": "Đường Hoàng Bích Sơn",
            "is_picked": "",
            "is_delivered": 1,
            "lat": "10.9383013",
            "lng": "108.11138040000003"
        },
        {
            "id": 991124,
            "name": "Đường Huỳnh Thị Khá",
            "pid": 15101,
            "type": 21,
            "region": null,
            "alias": "Đường Huỳnh Thị Khá",
            "is_picked": 1,
            "is_delivered": 1,
            "lat": "10.9383013",
            "lng": "108.11138040000003"
        },
        {
            "id": 568632,
            "name": "Đường Lâm Đình Trúc",
            "pid": 15101,
            "type": 21,
            "region": null,
            "alias": "Đường Lâm Đình Trúc",
            "is_picked": 1,
            "is_delivered": 1,
            "lat": "10.9383013",
            "lng": "108.11138040000003"
        },
        {
            "id": 568713,
            "name": "Đường Lê Đại Hành",
            "pid": 15101,
            "type": 21,
            "region": null,
            "alias": "Đường Lê Đại Hành",
            "is_picked": "",
            "is_delivered": 1,
            "lat": "10.9383013",
            "lng": "108.11138040000003"
        },
        {
            "id": 568650,
            "name": "Đường Lê Quý Đôn",
            "pid": 15101,
            "type": 16,
            "region": null,
            "alias": "Đường Lê Quý Đôn",
            "is_picked": 1,
            "is_delivered": 1,
            "lat": "10.9383013",
            "lng": "108.11138040000003"
        },
        {
            "id": 792679,
            "name": "Đường Lê Thanh Nghị",
            "pid": 15101,
            "type": 21,
            "region": null,
            "alias": "Đường Lê Thanh Nghị",
            "is_picked": "",
            "is_delivered": 1,
            "lat": "10.9383013",
            "lng": "108.11138040000004"
        },
        {
            "id": 568701,
            "name": "Đường Lê Trọng Tấn",
            "pid": 15101,
            "type": 21,
            "region": null,
            "alias": "Đường Lê Trọng Tấn",
            "is_picked": "",
            "is_delivered": 1,
            "lat": "10.9383013",
            "lng": "108.11138040000003"
        },
        {
            "id": 807052,
            "name": "Đường Lê Văn Hưu",
            "pid": 15101,
            "type": 21,
            "region": null,
            "alias": "đường Lê Văn Hưu",
            "is_picked": "",
            "is_delivered": 1,
            "lat": "10.9383013",
            "lng": "108.11138040000004"
        },
        {
            "id": 568722,
            "name": "Đường\n Lê Văn Lương",
            "pid": 15101,
            "type": 21,
            "region": null,
            "alias": "Đường\n Lê Văn Lương",
            "is_picked": "",
            "is_delivered": 1,
            "lat": "10.9383013",
            "lng": "108.11138040000003"
        },
        {
            "id": 854596,
            "name": "Đường Lê Văn Phấn",
            "pid": 15101,
            "type": 21,
            "region": null,
            "alias": "Đường Lê Văn Phấn",
            "is_picked": "",
            "is_delivered": 1,
            "lat": "10.938490",
            "lng": "108.111358"
        },
        {
            "id": 568596,
            "name": "Đường Lê Văn Thiêm",
            "pid": 15101,
            "type": 21,
            "region": null,
            "alias": "Đường Lê Văn Thiêm",
            "is_picked": 1,
            "is_delivered": 1,
            "lat": "10.9383013",
            "lng": "108.11138040000003"
        },
        {
            "id": 854599,
            "name": "Đường Lương Thế Vinh",
            "pid": 15101,
            "type": 21,
            "region": null,
            "alias": "Đường Lương Thế Vinh",
            "is_picked": 1,
            "is_delivered": 1,
            "lat": "10.938490",
            "lng": "108.111358"
        },
        {
            "id": 568584,
            "name": "Đường Lý Đạo Thành",
            "pid": 15101,
            "type": 21,
            "region": null,
            "alias": "Đường Lý Đạo Thành",
            "is_picked": 1,
            "is_delivered": 1,
            "lat": "10.9383013",
            "lng": "108.11138040000003"
        },
        {
            "id": 568674,
            "name": "Đường Mạc Đĩnh Chi",
            "pid": 15101,
            "type": 21,
            "region": null,
            "alias": "Đường Mạc Đĩnh Chi",
            "is_picked": "",
            "is_delivered": 1,
            "lat": "10.9383013",
            "lng": "108.11138040000003"
        },
        {
            "id": 568608,
            "name": "Đường Mai Trúc Loan",
            "pid": 15101,
            "type": 21,
            "region": null,
            "alias": "Đường Mai Trúc Loan",
            "is_picked": 1,
            "is_delivered": 1,
            "lat": "10.9383013",
            "lng": "108.11138040000003"
        },
        {
            "id": 568611,
            "name": "Đường Ngo Thì Nhậm",
            "pid": 15101,
            "type": 21,
            "region": null,
            "alias": "Đường Ngo Thì Nhậm",
            "is_picked": "",
            "is_delivered": 1,
            "lat": "10.9383013",
            "lng": "108.11138040000003"
        },
        {
            "id": 568653,
            "name": "Đường Nguyễn Biểu",
            "pid": 15101,
            "type": 21,
            "region": null,
            "alias": "Đường Nguyễn Biểu",
            "is_picked": "",
            "is_delivered": 1,
            "lat": "10.9383013",
            "lng": "108.11138040000003"
        },
        {
            "id": 568662,
            "name": "Đường Nguyễn Bỉnh Khiêm",
            "pid": 15101,
            "type": 21,
            "region": null,
            "alias": "Đường Nguyễn Bỉnh Khiêm",
            "is_picked": "",
            "is_delivered": 1,
            "lat": "10.9383013",
            "lng": "108.11138040000003"
        },
        {
            "id": 568671,
            "name": "Đường Nguyễn Cư Trinh",
            "pid": 15101,
            "type": 21,
            "region": null,
            "alias": "Đường Nguyễn Cư Trinh",
            "is_picked": "",
            "is_delivered": 1,
            "lat": "10.9383013",
            "lng": "108.11138040000003"
        },
        {
            "id": 568731,
            "name": "Đường Nguyên Hồng",
            "pid": 15101,
            "type": 21,
            "region": null,
            "alias": "Đường Nguyên Hồng",
            "is_picked": "",
            "is_delivered": 1,
            "lat": "10.9383013",
            "lng": "108.11138040000003"
        },
        {
            "id": 568665,
            "name": "Đường Nguyễn Huy Tự",
            "pid": 15101,
            "type": 21,
            "region": null,
            "alias": "Đường Nguyễn Huy Tự",
            "is_picked": "",
            "is_delivered": 1,
            "lat": "10.9383013",
            "lng": "108.11138040000003"
        },
        {
            "id": 568692,
            "name": "Đường Nguyễn Phúc Nguyên",
            "pid": 15101,
            "type": 21,
            "region": null,
            "alias": "Đường Nguyễn Phúc Nguyên",
            "is_picked": 1,
            "is_delivered": 1,
            "lat": "10.9383013",
            "lng": "108.11138040000003"
        },
        {
            "id": 854602,
            "name": "Đường Nguyễn Quý Đôn",
            "pid": 15101,
            "type": 21,
            "region": null,
            "alias": "Đường Nguyễn Quý Đôn",
            "is_picked": "",
            "is_delivered": 1,
            "lat": "10.938490",
            "lng": "108.111358"
        },
        {
            "id": 568599,
            "name": "Đường Nguyễn Sắc Kim",
            "pid": 15101,
            "type": 21,
            "region": null,
            "alias": "Đường Nguyễn Sắc Kim",
            "is_picked": 1,
            "is_delivered": 1,
            "lat": "10.9383013",
            "lng": "108.11138040000003"
        },
        {
            "id": 792685,
            "name": "Đường Nguyễn Thế Lâm",
            "pid": 15101,
            "type": 21,
            "region": null,
            "alias": "đường Nguyễn Thế Lâm",
            "is_picked": "",
            "is_delivered": 1,
            "lat": "10.9383013",
            "lng": "108.11138040000004"
        },
        {
            "id": 568677,
            "name": "Đường Nguyễn Tương",
            "pid": 15101,
            "type": 21,
            "region": null,
            "alias": "Đường Nguyễn Tương",
            "is_picked": "",
            "is_delivered": 1,
            "lat": "10.9383013",
            "lng": "108.11138040000003"
        },
        {
            "id": 711766,
            "name": "Đường Nguyễn Văn Huyên",
            "pid": 15101,
            "type": 21,
            "region": null,
            "alias": "Đường Nguyễn Văn Huyên",
            "is_picked": "",
            "is_delivered": 1,
            "lat": "10.939070",
            "lng": "108.111319"
        },
        {
            "id": 568602,
            "name": "Đường Ông Ích Khiêm",
            "pid": 15101,
            "type": 21,
            "region": null,
            "alias": "Đường Ông Ích Khiêm",
            "is_picked": "",
            "is_delivered": 1,
            "lat": "10.9383013",
            "lng": "108.11138040000003"
        },
        {
            "id": 568698,
            "name": "Đường Phạm Hùng",
            "pid": 15101,
            "type": 21,
            "region": null,
            "alias": "Đường Phạm Hùng",
            "is_picked": "",
            "is_delivered": 1,
            "lat": "10.9383013",
            "lng": "108.11138040000003"
        },
        {
            "id": 568614,
            "name": "Đường Phan Trung",
            "pid": 15101,
            "type": 21,
            "region": null,
            "alias": "Đường Phan Trung",
            "is_picked": 1,
            "is_delivered": 1,
            "lat": "10.9383013",
            "lng": "108.11138040000003"
        },
        {
            "id": 568623,
            "name": "Đường Phùng Hưng",
            "pid": 15101,
            "type": 21,
            "region": null,
            "alias": "Đường Phùng Hưng",
            "is_picked": 1,
            "is_delivered": 1,
            "lat": "10.9383013",
            "lng": "108.11138040000003"
        },
        {
            "id": 568587,
            "name": "Đường Số 5",
            "pid": 15101,
            "type": 21,
            "region": null,
            "alias": "Đường Số 5",
            "is_picked": 1,
            "is_delivered": 1,
            "lat": "10.9383013",
            "lng": "108.11138040000003"
        },
        {
            "id": 568605,
            "name": "Đường Số 6",
            "pid": 15101,
            "type": 21,
            "region": null,
            "alias": "Đường Số 6",
            "is_picked": 1,
            "is_delivered": 1,
            "lat": "10.9383013",
            "lng": "108.11138040000003"
        },
        {
            "id": 568590,
            "name": "Đường Thủ Khoa Huân",
            "pid": 15101,
            "type": 21,
            "region": null,
            "alias": "Đường Thủ Khoa Huân",
            "is_picked": "",
            "is_delivered": 1,
            "lat": "10.9383013",
            "lng": "108.11138040000003"
        },
        {
            "id": 992317,
            "name": "Đường Thủ Khoa Huân (25-187)",
            "pid": 15101,
            "type": 21,
            "region": null,
            "alias": "Đường Thủ Khoa Huân (25-187)",
            "is_picked": 1,
            "is_delivered": 1,
            "lat": "10.9383013",
            "lng": "108.11138040000003"
        },
        {
            "id": 568572,
            "name": "Đường Tôn Đức Thắng",
            "pid": 15101,
            "type": 5,
            "region": null,
            "alias": "Đường Tôn Đức Thắng",
            "is_picked": 1,
            "is_delivered": 1,
            "lat": "10.9383013",
            "lng": "108.11138040000003"
        },
        {
            "id": 568659,
            "name": "Đường Trần Hưng Đạo",
            "pid": 15101,
            "type": 21,
            "region": null,
            "alias": "Đường Trần Hưng Đạo",
            "is_picked": 1,
            "is_delivered": 1,
            "lat": "10.9383013",
            "lng": "108.11138040000003"
        },
        {
            "id": 568668,
            "name": "Đường Trần Văn Lương (01-07, 02-18)",
            "pid": 15101,
            "type": 21,
            "region": null,
            "alias": "Đường Trần Văn Lương (01-07, 02-18)",
            "is_picked": 1,
            "is_delivered": 1,
            "lat": "10.9383013",
            "lng": "108.11138040000003"
        },
        {
            "id": 568704,
            "name": "Đường Trương Hán Siêu",
            "pid": 15101,
            "type": 21,
            "region": null,
            "alias": "Đường Trương Hán Siêu",
            "is_picked": 1,
            "is_delivered": 1,
            "lat": "10.9383013",
            "lng": "108.11138040000003"
        },
        {
            "id": 568644,
            "name": "Đường Tuyên Quang",
            "pid": 15101,
            "type": 5,
            "region": null,
            "alias": "Đường Tuyên Quang",
            "is_picked": 1,
            "is_delivered": 1,
            "lat": "10.9383013",
            "lng": "108.11138040000003"
        },
        {
            "id": 568710,
            "name": "Đường\n Viettel",
            "pid": 15101,
            "type": 4,
            "region": null,
            "alias": "Đường\n Viettel",
            "is_picked": "",
            "is_delivered": 1,
            "lat": "10.9383013",
            "lng": "108.11138040000003"
        },
        {
            "id": 568647,
            "name": "Đường Võ Hữu",
            "pid": 15101,
            "type": 21,
            "region": null,
            "alias": "Đường Võ Hữu",
            "is_picked": 1,
            "is_delivered": 1,
            "lat": "10.9383013",
            "lng": "108.11138040000003"
        },
        {
            "id": 568620,
            "name": "Đường Võ Liêm Sơn",
            "pid": 15101,
            "type": 21,
            "region": null,
            "alias": "Đường Võ Liêm Sơn",
            "is_picked": 1,
            "is_delivered": 1,
            "lat": "10.9383013",
            "lng": "108.11138040000003"
        },
        {
            "id": 920740,
            "name": "Hoàng Hoa Thám",
            "pid": 15101,
            "type": 21,
            "region": null,
            "alias": "Hoàng Hoa Thám",
            "is_picked": 1,
            "is_delivered": 1,
            "lat": "10.9383013",
            "lng": "108.11138040000004"
        },
        {
            "id": 996421,
            "name": "Kdc Hùng Vương 2",
            "pid": 15101,
            "type": 21,
            "region": null,
            "alias": "KDC Hùng Vương 2",
            "is_picked": 1,
            "is_delivered": 1,
            "lat": "10.9383013",
            "lng": "108.11138040000004"
        },
        {
            "id": 996426,
            "name": "L1-L2 Đông Xuân An",
            "pid": 15101,
            "type": 21,
            "region": null,
            "alias": "L1-L2 Đông Xuân An",
            "is_picked": 1,
            "is_delivered": 1,
            "lat": "10.9383013",
            "lng": "108.11138040000004"
        },
        {
            "id": 568695,
            "name": "Lô A- Lô C Nguyễn Gia Tú",
            "pid": 15101,
            "type": 21,
            "region": null,
            "alias": "Lô A- Lô C Nguyễn Gia Tú",
            "is_picked": "",
            "is_delivered": 1,
            "lat": "10.9383013",
            "lng": "108.11138040000003"
        },
        {
            "id": 568629,
            "name": "Lô A-Lô F Hùng Vương",
            "pid": 15101,
            "type": 21,
            "region": null,
            "alias": "Lô A-Lô F Hùng Vương",
            "is_picked": 1,
            "is_delivered": 1,
            "lat": "10.9383013",
            "lng": "108.11138040000003"
        },
        {
            "id": 996423,
            "name": "Lô B Nguyễn Gia Tú",
            "pid": 15101,
            "type": 21,
            "region": null,
            "alias": "Lô B Nguyễn Gia Tú",
            "is_picked": 1,
            "is_delivered": 1,
            "lat": "10.9383013",
            "lng": "108.11138040000004"
        },
        {
            "id": 792676,
            "name": "Lô D - Lô E Nguyễn Gia Tú",
            "pid": 15101,
            "type": 21,
            "region": null,
            "alias": "Lô D - Lô E Nguyễn Gia Tú",
            "is_picked": "",
            "is_delivered": 1,
            "lat": "10.9383013",
            "lng": "108.11138040000004"
        },
        {
            "id": 757201,
            "name": "Lưu Hữu Phước",
            "pid": 15101,
            "type": 21,
            "region": null,
            "alias": "Lưu Hữu Phước",
            "is_picked": "",
            "is_delivered": 1,
            "lat": "10.9383013",
            "lng": "108.11138040000004"
        },
        {
            "id": 996391,
            "name": "Nguyễn Trãi Nối Dài",
            "pid": 15101,
            "type": 21,
            "region": null,
            "alias": "Nguyễn Trãi nối dài",
            "is_picked": 1,
            "is_delivered": 1,
            "lat": "10.9383013",
            "lng": "108.11138040000003"
        },
        {
            "id": 852868,
            "name": "Tòa Nhà Viettel",
            "pid": 15101,
            "type": 4,
            "region": null,
            "alias": "Tòa Nhà Viettel",
            "is_picked": 1,
            "is_delivered": 1,
            "lat": "10.938321",
            "lng": "108.111336"
        },
        {
            "id": 996419,
            "name": "Tôn Thất Tùng",
            "pid": 15101,
            "type": 21,
            "region": null,
            "alias": "Tôn Thất Tùng",
            "is_picked": 1,
            "is_delivered": 1,
            "lat": "10.9383013",
            "lng": "108.11138040000004"
        },
        {
            "id": 996420,
            "name": "Tuệ Tĩnh",
            "pid": 15101,
            "type": 21,
            "region": null,
            "alias": "Tuệ Tĩnh",
            "is_picked": 1,
            "is_delivered": 1,
            "lat": "10.9383013",
            "lng": "108.11138040000004"
        },
        {
            "id": 568689,
            "name": "Võ Văn Kiệt (2-80, 1-209)",
            "pid": 15101,
            "type": 21,
            "region": null,
            "alias": "Võ Văn Kiệt (2-80, 1-209)",
            "is_picked": "",
            "is_delivered": 1,
            "lat": "10.9383013",
            "lng": "108.11138040000003"
        },
        {
            "id": 996424,
            "name": "Võ Văn Kiệt (86-400, 255-353)",
            "pid": 15101,
            "type": 21,
            "region": null,
            "alias": "Võ Văn kiệt (86-400, 255-353)",
            "is_picked": 1,
            "is_delivered": 1,
            "lat": "10.9383013",
            "lng": "108.11138040000004"
        }
    ],
    "log_id": "67581477ea8ec31"
}