{
    "success": true,
    "message": "Get list address success!",
    "data": [
        {
            "id": 875479,
            "name": "Bưu Điện Xã",
            "pid": 18548,
            "type": 16,
            "region": null,
            "alias": "Bưu Điện Xã",
            "is_picked": "",
            "is_delivered": 1,
            "lat": "13°31'18.6\"N",
            "lng": "108°06'14.1\"E"
        },
        {
            "id": 625422,
            "name": "Thôn Brieng",
            "pid": 18548,
            "type": 16,
            "region": null,
            "alias": "Thôn Brieng",
            "is_picked": "",
            "is_delivered": 1,
            "lat": "13.5019781",
            "lng": "108.15472599999998"
        },
        {
            "id": 625419,
            "name": "Thôn Chư Bông",
            "pid": 18548,
            "type": 16,
            "region": null,
            "alias": "Thôn Chư Bông",
            "is_picked": "",
            "is_delivered": 1,
            "lat": "13.5019781",
            "lng": "108.15472599999998"
        },
        {
            "id": 625413,
            "name": "Thôn Chư Pố 1",
            "pid": 18548,
            "type": 16,
            "region": null,
            "alias": "Thôn Chư Pố 1",
            "is_picked": "",
            "is_delivered": 1,
            "lat": "13.5019781",
            "lng": "108.15472599999998"
        },
        {
            "id": 625416,
            "name": "Thôn Chư Pố 2",
            "pid": 18548,
            "type": 16,
            "region": null,
            "alias": "Thôn Chư Pố 2",
            "is_picked": "",
            "is_delivered": 1,
            "lat": "13.5019781",
            "lng": "108.15472599999998"
        },
        {
            "id": 625404,
            "name": "Thôn Hoà Lộc",
            "pid": 18548,
            "type": 16,
            "region": null,
            "alias": "Thôn Hoà Lộc",
            "is_picked": "",
            "is_delivered": 1,
            "lat": "13.5019781",
            "lng": "108.15472599999998"
        },
        {
            "id": 625398,
            "name": "Thôn Hoà Sơn",
            "pid": 18548,
            "type": 16,
            "region": null,
            "alias": "Thôn Hoà Sơn",
            "is_picked": "",
            "is_delivered": 1,
            "lat": "13.5019781",
            "lng": "108.15472599999998"
        },
        {
            "id": 625428,
            "name": "Thôn Hoà Thuận",
            "pid": 18548,
            "type": 16,
            "region": null,
            "alias": "Thôn Hoà Thuận",
            "is_picked": "",
            "is_delivered": 1,
            "lat": "13.5019781",
            "lng": "108.15472599999998"
        },
        {
            "id": 625425,
            "name": "Thôn Ia Ke",
            "pid": 18548,
            "type": 16,
            "region": null,
            "alias": "Thôn Ia Ke",
            "is_picked": "",
            "is_delivered": 1,
            "lat": "13.5019781",
            "lng": "108.15472599999998"
        },
        {
            "id": 878113,
            "name": "Thôn Plei Phung A",
            "pid": 18548,
            "type": 16,
            "region": null,
            "alias": "Thôn Plei Phung A",
            "is_picked": "",
            "is_delivered": 1,
            "lat": "13.5019781",
            "lng": "108.15472599999998"
        },
        {
            "id": 625395,
            "name": "Thôn Pley Phung B",
            "pid": 18548,
            "type": 16,
            "region": null,
            "alias": "Thôn Pley Phung B",
            "is_picked": "",
            "is_delivered": 1,
            "lat": "13.5019781",
            "lng": "108.15472599999998"
        },
        {
            "id": 625410,
            "name": "Thôn Pley Tao",
            "pid": 18548,
            "type": 16,
            "region": null,
            "alias": "Thôn Pley Tao",
            "is_picked": "",
            "is_delivered": 1,
            "lat": "13.5019781",
            "lng": "108.15472599999998"
        },
        {
            "id": 625407,
            "name": "Thôn Pley Thonhuen",
            "pid": 18548,
            "type": 16,
            "region": null,
            "alias": "Thôn Pley Thonhuen",
            "is_picked": "",
            "is_delivered": 1,
            "lat": "13.5019781",
            "lng": "108.15472599999998"
        }
    ],
    "log_id": "675816d3605b1307"
}