{
    "success": true,
    "message": "Get list address success!",
    "data": [
        {
            "id": 848812,
            "name": "Ban Chỉ Huy Quân Sự Huyện Mường Nhé",
            "pid": 22046,
            "type": 20,
            "region": null,
            "alias": "Ban Chỉ Huy Quân Sự Huyện Mường Nhé",
            "is_picked": "",
            "is_delivered": 1,
            "lat": "22.165985600000006",
            "lng": "102.41513350000002"
        },
        {
            "id": 864892,
            "name": "Bản Huổi Ban",
            "pid": 22046,
            "type": 16,
            "region": null,
            "alias": "Bản Huổi Ban",
            "is_picked": "",
            "is_delivered": 1,
            "lat": "22.165985600000006",
            "lng": "102.41513350000002"
        },
        {
            "id": 832918,
            "name": "Bản Mường Nhé",
            "pid": 22046,
            "type": 16,
            "region": null,
            "alias": "Bản Mường Nhé",
            "is_picked": "",
            "is_delivered": 1,
            "lat": "22.165985600000006",
            "lng": "102.41513350000002"
        },
        {
            "id": 586446,
            "name": "Bản Mường Nhé Mới",
            "pid": 22046,
            "type": 16,
            "region": null,
            "alias": "Bản Mường Nhé Mới",
            "is_picked": "",
            "is_delivered": 1,
            "lat": "22.1659856",
            "lng": "102.41513350000002"
        },
        {
            "id": 864910,
            "name": "Bản Mường Toong",
            "pid": 22046,
            "type": 16,
            "region": null,
            "alias": "Bản Mường Toong",
            "is_picked": "",
            "is_delivered": 1,
            "lat": "22.165985600000006",
            "lng": "102.41513350000002"
        },
        {
            "id": 864898,
            "name": "Bản Nậm Là",
            "pid": 22046,
            "type": 16,
            "region": null,
            "alias": "Bản Nậm Là",
            "is_picked": "",
            "is_delivered": 1,
            "lat": "22.165985600000006",
            "lng": "102.41513350000002"
        },
        {
            "id": 838084,
            "name": "Bản Nậm San",
            "pid": 22046,
            "type": 16,
            "region": null,
            "alias": "Bản Nậm San",
            "is_picked": "",
            "is_delivered": 1,
            "lat": "22.165985600000006",
            "lng": "102.41513350000002"
        },
        {
            "id": 838096,
            "name": "Bản Nậm San 2",
            "pid": 22046,
            "type": 16,
            "region": null,
            "alias": "bản nậm san 2",
            "is_picked": "",
            "is_delivered": 1,
            "lat": "22.165985600000006",
            "lng": "102.41513350000002"
        },
        {
            "id": 838075,
            "name": "Bản Phiêng Kham",
            "pid": 22046,
            "type": 16,
            "region": null,
            "alias": "Bản Phiêng Kham",
            "is_picked": "",
            "is_delivered": 1,
            "lat": "22.165985600000006",
            "lng": "102.41513350000002"
        },
        {
            "id": 849997,
            "name": "Bảo Hiểm Xã Hội Huyện Mường Nhé",
            "pid": 22046,
            "type": 16,
            "region": null,
            "alias": "Bảo Hiểm Xã Hội Huyện Mường Nhé",
            "is_picked": "",
            "is_delivered": 1,
            "lat": "22.1659856",
            "lng": "102.41513350000002"
        },
        {
            "id": 873571,
            "name": "Cảnh Sát Cơ Động",
            "pid": 22046,
            "type": 16,
            "region": null,
            "alias": "Cảnh Sát Cơ động",
            "is_picked": "",
            "is_delivered": 1,
            "lat": "22.165985600000006",
            "lng": "102.41513350000002"
        },
        {
            "id": 864895,
            "name": "Chi Cục Thì Hành Án Dân Sự",
            "pid": 22046,
            "type": 20,
            "region": null,
            "alias": "Chi Cục Thì Hành án Dân Sự",
            "is_picked": "",
            "is_delivered": 1,
            "lat": "22.165985600000006",
            "lng": "102.41513350000002"
        },
        {
            "id": 864901,
            "name": "Chị Cục Thuế Huyện Mường Nhé",
            "pid": 22046,
            "type": 20,
            "region": null,
            "alias": "Chị Cục Thuế Huyện Mường Nhé",
            "is_picked": "",
            "is_delivered": 1,
            "lat": "22.165985600000006",
            "lng": "102.41513350000002"
        },
        {
            "id": 854419,
            "name": "Chợ Mường Nhé",
            "pid": 22046,
            "type": 20,
            "region": null,
            "alias": "Chợ mường nhé",
            "is_picked": "",
            "is_delivered": 1,
            "lat": "22.1659856",
            "lng": "102.41513350000002"
        },
        {
            "id": 845065,
            "name": "Co Lót 1",
            "pid": 22046,
            "type": 16,
            "region": null,
            "alias": "Co Lót 1",
            "is_picked": "",
            "is_delivered": 1,
            "lat": "22.165985600000006",
            "lng": "102.41513350000002"
        },
        {
            "id": 901483,
            "name": "Cty Tnhh Nam Thành",
            "pid": 22046,
            "type": 16,
            "region": null,
            "alias": "CTY Tnhh Nam Thành",
            "is_picked": "",
            "is_delivered": 1,
            "lat": "22.165985600000006",
            "lng": "102.41513350000002"
        },
        {
            "id": 864907,
            "name": "Đại Đội Cảnh Sát Cơ Động",
            "pid": 22046,
            "type": 16,
            "region": null,
            "alias": "Đại đội cảnh sát cơ động",
            "is_picked": "",
            "is_delivered": 1,
            "lat": "22.165985600000006",
            "lng": "102.41513350000002"
        },
        {
            "id": 849991,
            "name": "Điện Lực Mường Nhé",
            "pid": 22046,
            "type": 16,
            "region": null,
            "alias": "Điện Lực Mường Nhé",
            "is_picked": "",
            "is_delivered": 1,
            "lat": "22.1659856",
            "lng": "102.41513350000002"
        },
        {
            "id": 850000,
            "name": "Kho Bạc Mường Nhé",
            "pid": 22046,
            "type": 20,
            "region": null,
            "alias": "Kho Bạc Mường Nhé",
            "is_picked": "",
            "is_delivered": 1,
            "lat": "22.1659856",
            "lng": "102.41513350000002"
        },
        {
            "id": 586452,
            "name": "Mường Nhé 2",
            "pid": 22046,
            "type": 16,
            "region": null,
            "alias": "Mường Nhé 2",
            "is_picked": "",
            "is_delivered": 1,
            "lat": "22.1659856",
            "lng": "102.41513350000002"
        },
        {
            "id": 864889,
            "name": "Nậm Pố",
            "pid": 22046,
            "type": 16,
            "region": null,
            "alias": "Nậm Pố",
            "is_picked": "",
            "is_delivered": 1,
            "lat": "22.165985600000006",
            "lng": "102.41513350000002"
        },
        {
            "id": 586434,
            "name": "Nậm Pố 1",
            "pid": 22046,
            "type": 16,
            "region": null,
            "alias": "Nậm Pố 1",
            "is_picked": "",
            "is_delivered": 1,
            "lat": "22.1659856",
            "lng": "102.41513350000002"
        },
        {
            "id": 848815,
            "name": "Nhà Khách Trúc An",
            "pid": 22046,
            "type": 20,
            "region": null,
            "alias": "Nhà Khách Trúc An",
            "is_picked": "",
            "is_delivered": 1,
            "lat": "22.165985600000006",
            "lng": "102.41513350000002"
        },
        {
            "id": 864904,
            "name": "Phòng Dân Tộc",
            "pid": 22046,
            "type": 16,
            "region": null,
            "alias": "Phòng dân tộc",
            "is_picked": "",
            "is_delivered": 1,
            "lat": "22.165985600000006",
            "lng": "102.41513350000002"
        },
        {
            "id": 901486,
            "name": "Phòng Tài Chính Kế Hoạch",
            "pid": 22046,
            "type": 16,
            "region": null,
            "alias": "Phòng Tài Chính Kế Hoạch",
            "is_picked": "",
            "is_delivered": 1,
            "lat": "22.165985600000006",
            "lng": "102.41513350000002"
        },
        {
            "id": 849994,
            "name": "Sân Vận Động Huyện Mường Nhé",
            "pid": 22046,
            "type": 16,
            "region": null,
            "alias": "Sân Vận động Huyện Mường Nhé",
            "is_picked": "",
            "is_delivered": 1,
            "lat": "22.1659856",
            "lng": "102.41513350000002"
        },
        {
            "id": 873565,
            "name": "Thôn Huổi Cọ",
            "pid": 22046,
            "type": 16,
            "region": null,
            "alias": "Thôn Huổi Cọ",
            "is_picked": "",
            "is_delivered": 1,
            "lat": "22.165985600000006",
            "lng": "102.41513350000002"
        },
        {
            "id": 840208,
            "name": "Thôn Mường Nhé",
            "pid": 22046,
            "type": 16,
            "region": null,
            "alias": "Thôn Mường Nhé",
            "is_picked": "",
            "is_delivered": 1,
            "lat": "22.165985600000006",
            "lng": "102.41513350000002"
        },
        {
            "id": 586449,
            "name": "Thôn Mường Nhé 1",
            "pid": 22046,
            "type": 16,
            "region": null,
            "alias": "Thôn Mường Nhé 1",
            "is_picked": "",
            "is_delivered": 1,
            "lat": "22.1659856",
            "lng": "102.41513350000002"
        },
        {
            "id": 586437,
            "name": "Thôn Nậm Pố 2",
            "pid": 22046,
            "type": 16,
            "region": null,
            "alias": "thôn Nậm Pố 2",
            "is_picked": "",
            "is_delivered": 1,
            "lat": "22.1659856",
            "lng": "102.41513350000002"
        },
        {
            "id": 586440,
            "name": "Thôn Nậm Pố 3",
            "pid": 22046,
            "type": 16,
            "region": null,
            "alias": "Thôn Nậm Pố 3",
            "is_picked": "",
            "is_delivered": 1,
            "lat": "22.1659856",
            "lng": "102.41513350000002"
        },
        {
            "id": 586443,
            "name": "Thôn Nậm Pố 4",
            "pid": 22046,
            "type": 16,
            "region": null,
            "alias": "Thôn Nậm Pố 4",
            "is_picked": "",
            "is_delivered": 1,
            "lat": "22.1659856",
            "lng": "102.41513350000002"
        },
        {
            "id": 586458,
            "name": "Thôn Nậm Sam 1",
            "pid": 22046,
            "type": 16,
            "region": null,
            "alias": "Thôn Nậm Sam 1",
            "is_picked": "",
            "is_delivered": 1,
            "lat": "22.1659856",
            "lng": "102.41513350000002"
        },
        {
            "id": 586461,
            "name": "Thôn Nậm San 2",
            "pid": 22046,
            "type": 16,
            "region": null,
            "alias": "Thôn Nậm San 2",
            "is_picked": "",
            "is_delivered": 1,
            "lat": "22.1659856",
            "lng": "102.41513350000002"
        },
        {
            "id": 586455,
            "name": "Thôn Nà Páng",
            "pid": 22046,
            "type": 16,
            "region": null,
            "alias": "Thôn Nà Páng",
            "is_picked": "",
            "is_delivered": 1,
            "lat": "22.1659856",
            "lng": "102.41513350000002"
        },
        {
            "id": 845074,
            "name": "Thôn Phiên Kham",
            "pid": 22046,
            "type": 16,
            "region": null,
            "alias": "Thôn Phiên Kham",
            "is_picked": "",
            "is_delivered": 1,
            "lat": "22.165985600000006",
            "lng": "102.41513350000002"
        },
        {
            "id": 838099,
            "name": "Tổ 2",
            "pid": 22046,
            "type": 20,
            "region": null,
            "alias": "Tổ 2",
            "is_picked": "",
            "is_delivered": 1,
            "lat": "22.165985600000006",
            "lng": "102.41513350000002"
        },
        {
            "id": 832915,
            "name": "Toà Án Nhân Dân Huyện Mường Nhé",
            "pid": 22046,
            "type": 20,
            "region": null,
            "alias": "Toà án Nhân Dân Huyện Mường Nhé",
            "is_picked": "",
            "is_delivered": 1,
            "lat": "22.165985600000006",
            "lng": "102.41513350000002"
        },
        {
            "id": 854410,
            "name": "Tòa Nhà Phòng Giáo Dục Và Đào Tạo Huyện Mường Nhé",
            "pid": 22046,
            "type": 4,
            "region": null,
            "alias": "tòa nhà PHÒNG GIÁO DỤC VÀ ĐÀO TẠO HUYỆN MƯỜNG NHÉ",
            "is_picked": "",
            "is_delivered": 1,
            "lat": "22.1659856",
            "lng": "102.41513350000002"
        },
        {
            "id": 854416,
            "name": "Tòa Nhà Phòng Văn Hóa Thông Tin Mường Nhé",
            "pid": 22046,
            "type": 4,
            "region": null,
            "alias": "tòa nhà Phòng Văn Hóa Thông Tin Mường Nhé",
            "is_picked": "",
            "is_delivered": 1,
            "lat": "22.1659856",
            "lng": "102.41513350000002"
        },
        {
            "id": 854404,
            "name": "Tòa Nhà Trung Tâm Chính Trị Huyện Mường Nhé",
            "pid": 22046,
            "type": 4,
            "region": null,
            "alias": "tòa nhà Trung Tâm Chính Trị Huyện Mường Nhé",
            "is_picked": "",
            "is_delivered": 1,
            "lat": "22.1659856",
            "lng": "102.41513350000002"
        },
        {
            "id": 854413,
            "name": "Tòa Nhà Ubnd Xã Mường Nhé",
            "pid": 22046,
            "type": 4,
            "region": null,
            "alias": "tòa nhà Ubnd Xã Mường Nhé",
            "is_picked": "",
            "is_delivered": 1,
            "lat": "22.1659856",
            "lng": "102.41513350000002"
        },
        {
            "id": 848806,
            "name": "Tổ Dân Cư Số 1",
            "pid": 22046,
            "type": 20,
            "region": null,
            "alias": "Tổ Dân Cư Số 1",
            "is_picked": "",
            "is_delivered": 1,
            "lat": "22.165985600000006",
            "lng": "102.41513350000002"
        },
        {
            "id": 838093,
            "name": "Tổ Dân Cư Số 2",
            "pid": 22046,
            "type": 20,
            "region": null,
            "alias": "Tổ Dân Cư Số 2",
            "is_picked": "",
            "is_delivered": 1,
            "lat": "22.165985600000006",
            "lng": "102.41513350000002"
        },
        {
            "id": 848809,
            "name": "Tổ Dân Cư Số 3",
            "pid": 22046,
            "type": 20,
            "region": null,
            "alias": "Tổ Dân Cư Số 3",
            "is_picked": "",
            "is_delivered": 1,
            "lat": "22.165985600000006",
            "lng": "102.41513350000002"
        },
        {
            "id": 838078,
            "name": "Tổ Dân Phố 2",
            "pid": 22046,
            "type": 20,
            "region": null,
            "alias": "Tổ Dân Phố 2",
            "is_picked": "",
            "is_delivered": 1,
            "lat": "22.165985600000006",
            "lng": "102.41513350000002"
        },
        {
            "id": 854407,
            "name": "Tổ Dân Phố Số 3",
            "pid": 22046,
            "type": 20,
            "region": null,
            "alias": "Tổ Dân Phố Số 3",
            "is_picked": "",
            "is_delivered": 1,
            "lat": "22.1659856",
            "lng": "102.41513350000002"
        },
        {
            "id": 873574,
            "name": "Trực An 6",
            "pid": 22046,
            "type": 20,
            "region": null,
            "alias": "Trực An 6",
            "is_picked": "",
            "is_delivered": 1,
            "lat": "22.165985600000006",
            "lng": "102.41513350000002"
        },
        {
            "id": 838081,
            "name": "Trung Tâm Huyện Mường Nhé",
            "pid": 22046,
            "type": 20,
            "region": null,
            "alias": "Trung Tâm Huyện Mường Nhé",
            "is_picked": "",
            "is_delivered": 1,
            "lat": "22.165985600000006",
            "lng": "102.41513350000002"
        },
        {
            "id": 840214,
            "name": "Trung Tâm Thị Trấn",
            "pid": 22046,
            "type": 20,
            "region": null,
            "alias": "Trung Tâm Thị Trấn",
            "is_picked": "",
            "is_delivered": 1,
            "lat": "22.165985600000006",
            "lng": "102.41513350000002"
        },
        {
            "id": 840211,
            "name": "Trung Tâm Y Tế",
            "pid": 22046,
            "type": 16,
            "region": null,
            "alias": "Trung Tâm Y Tế",
            "is_picked": "",
            "is_delivered": 1,
            "lat": "22.165985600000006",
            "lng": "102.41513350000002"
        },
        {
            "id": 838087,
            "name": "Trung Tâm Y Tế Mường Nhé",
            "pid": 22046,
            "type": 16,
            "region": null,
            "alias": "Trung Tâm Y Tế Mường Nhé",
            "is_picked": "",
            "is_delivered": 1,
            "lat": "22.165985600000006",
            "lng": "102.41513350000002"
        },
        {
            "id": 873580,
            "name": "Trường Cấp 3",
            "pid": 22046,
            "type": 20,
            "region": null,
            "alias": "Trường Cấp 3",
            "is_picked": "",
            "is_delivered": 1,
            "lat": "22.165985600000006",
            "lng": "102.41513350000002"
        },
        {
            "id": 873568,
            "name": "Trường Mầm Non Hoa Ban",
            "pid": 22046,
            "type": 9,
            "region": null,
            "alias": "Trường Mầm Non Hoa Ban",
            "is_picked": "",
            "is_delivered": 1,
            "lat": "22.165985600000006",
            "lng": "102.41513350000002"
        },
        {
            "id": 845068,
            "name": "Trường Mầm Non Hoa Ban Huyện Mường Nhé",
            "pid": 22046,
            "type": 9,
            "region": null,
            "alias": "Trường Mầm Non Hoa Ban Huyện Mường Nhé",
            "is_picked": "",
            "is_delivered": 1,
            "lat": "22.165985600000006",
            "lng": "102.41513350000002"
        },
        {
            "id": 873577,
            "name": "Trường Mầm Non Mường Nhé",
            "pid": 22046,
            "type": 9,
            "region": null,
            "alias": "Trường Mầm Non Mường Nhé",
            "is_picked": "",
            "is_delivered": 1,
            "lat": "22.165985600000006",
            "lng": "102.41513350000002"
        },
        {
            "id": 838072,
            "name": "Trường Thpt Mường Nhé",
            "pid": 22046,
            "type": 20,
            "region": null,
            "alias": "Trường Thpt Mường Nhé",
            "is_picked": "",
            "is_delivered": 1,
            "lat": "22.165985600000006",
            "lng": "102.41513350000002"
        },
        {
            "id": 864886,
            "name": "Trường Tiểu Học Mường Nhé",
            "pid": 22046,
            "type": 9,
            "region": null,
            "alias": "Trường Tiểu Học Mường Nhé",
            "is_picked": "",
            "is_delivered": 1,
            "lat": "22.165985600000006",
            "lng": "102.41513350000002"
        },
        {
            "id": 845077,
            "name": "Trường Trần Văn Thọ",
            "pid": 22046,
            "type": 16,
            "region": null,
            "alias": "Trường Trần Văn Thọ",
            "is_picked": "",
            "is_delivered": 1,
            "lat": "22.165985600000006",
            "lng": "102.41513350000002"
        },
        {
            "id": 854422,
            "name": "Trường Trường Phổ Thông Dân Tộc Bán Trú Tiểu Học Nậm Vì",
            "pid": 22046,
            "type": 16,
            "region": null,
            "alias": "trường Trường Phổ thông dân tộc bán trú Tiểu học Nậm Vì",
            "is_picked": "",
            "is_delivered": 1,
            "lat": "22.1659856",
            "lng": "102.41513350000002"
        },
        {
            "id": 838090,
            "name": "Ubnd Huyện Mường Nhé",
            "pid": 22046,
            "type": 20,
            "region": null,
            "alias": "UBND huyện Mường Nhé",
            "is_picked": "",
            "is_delivered": 1,
            "lat": "22.165985600000006",
            "lng": "102.41513350000002"
        },
        {
            "id": 845071,
            "name": "Viện Kiểm Sát Nhân Dân",
            "pid": 22046,
            "type": 20,
            "region": null,
            "alias": "Viện kiểm sát nhân dân",
            "is_picked": "",
            "is_delivered": 1,
            "lat": "22.165985600000006",
            "lng": "102.41513350000002"
        }
    ],
    "log_id": "675816a587ece978"
}