{
    "success": true,
    "message": "Get list address success!",
    "data": [
        {
            "id": 476417,
            "name": "Thôn Ân Phú",
            "pid": 13635,
            "type": 16,
            "region": null,
            "alias": "Thôn Ân Phú",
            "is_picked": "",
            "is_delivered": 1,
            "lat": "21.1178311",
            "lng": "106.02875119999999"
        },
        {
            "id": 476421,
            "name": "Thôn Ấp Vang",
            "pid": 13635,
            "type": 16,
            "region": null,
            "alias": "Thôn Ấp Vang",
            "is_picked": "",
            "is_delivered": 1,
            "lat": "21.1178311",
            "lng": "106.02875119999999"
        },
        {
            "id": 476413,
            "name": "Thôn Đông Phù",
            "pid": 13635,
            "type": 16,
            "region": null,
            "alias": "Thôn Đông Phù",
            "is_picked": "",
            "is_delivered": 1,
            "lat": "21.1178311",
            "lng": "106.02875119999999"
        },
        {
            "id": 476411,
            "name": "Thôn Giới Tế",
            "pid": 13635,
            "type": 16,
            "region": null,
            "alias": "Thôn Giới Tế",
            "is_picked": "",
            "is_delivered": 1,
            "lat": "21.1178311",
            "lng": "106.02875119999999"
        },
        {
            "id": 476415,
            "name": "Thôn Hạ Giang",
            "pid": 13635,
            "type": 16,
            "region": null,
            "alias": "Thôn Hạ Giang",
            "is_picked": "",
            "is_delivered": 1,
            "lat": "21.1178311",
            "lng": "106.02875119999999"
        },
        {
            "id": 476409,
            "name": "Thôn Tam Tảo",
            "pid": 13635,
            "type": 16,
            "region": null,
            "alias": "Thôn Tam Tảo",
            "is_picked": "",
            "is_delivered": 1,
            "lat": "21.1178311",
            "lng": "106.02875119999999"
        },
        {
            "id": 476419,
            "name": "Thôn Vĩnh Phục",
            "pid": 13635,
            "type": 16,
            "region": null,
            "alias": "Thôn Vĩnh Phục",
            "is_picked": "",
            "is_delivered": 1,
            "lat": "21.1178311",
            "lng": "106.02875119999999"
        }
    ],
    "log_id": "675815f8ccfb3710"
}