{
    "success": true,
    "message": "Get list address success!",
    "data": [
        {
            "id": 429059,
            "name": "Bản Cao Sin Chải",
            "pid": 15526,
            "type": 16,
            "region": null,
            "alias": "Bản Cao Sin Chải",
            "is_picked": "",
            "is_delivered": 1,
            "lat": "22.6643063",
            "lng": "103.34717750000004"
        },
        {
            "id": 429019,
            "name": "Bản Gia Khâu",
            "pid": 15526,
            "type": 16,
            "region": null,
            "alias": "Bản Gia Khâu",
            "is_picked": "",
            "is_delivered": 1,
            "lat": "22.781158",
            "lng": "103.34717750000004"
        },
        {
            "id": 429085,
            "name": "Bản Mới 1",
            "pid": 15526,
            "type": 16,
            "region": null,
            "alias": "Bản Mới 1",
            "is_picked": "",
            "is_delivered": 1,
            "lat": "22.6643063",
            "lng": "103.34717750000004"
        },
        {
            "id": 429087,
            "name": "Bản Mới 2",
            "pid": 15526,
            "type": 16,
            "region": null,
            "alias": "Bản Mới 2",
            "is_picked": "",
            "is_delivered": 1,
            "lat": "22.6643063",
            "lng": "103.34717750000004"
        },
        {
            "id": 429083,
            "name": "Bản Tỷ Phùng",
            "pid": 15526,
            "type": 16,
            "region": null,
            "alias": "Bản Tỷ Phùng",
            "is_picked": "",
            "is_delivered": 1,
            "lat": "22.6643063",
            "lng": "103.34717750000004"
        },
        {
            "id": 736285,
            "name": "Bản Tỷ Phùng",
            "pid": 15526,
            "type": 16,
            "region": null,
            "alias": "Bản Tỷ Phùng",
            "is_picked": "",
            "is_delivered": 1,
            "lat": "22.781158",
            "lng": "103.34717750000004"
        },
        {
            "id": 429017,
            "name": "Bản Xin Chải",
            "pid": 15526,
            "type": 16,
            "region": null,
            "alias": "Bản Xin Chải",
            "is_picked": "",
            "is_delivered": 1,
            "lat": "22.781158",
            "lng": "103.34717750000004"
        },
        {
            "id": 429011,
            "name": "Lả Nhì Thàng",
            "pid": 15526,
            "type": 16,
            "region": null,
            "alias": "Lả Nhì Thàng",
            "is_picked": "",
            "is_delivered": 1,
            "lat": "22.781158",
            "lng": "103.34717750000004"
        },
        {
            "id": 429013,
            "name": "Lao Chải",
            "pid": 15526,
            "type": 16,
            "region": null,
            "alias": "Lao Chải",
            "is_picked": "",
            "is_delivered": 1,
            "lat": "22.781158",
            "lng": "103.34717750000004"
        },
        {
            "id": 429021,
            "name": "Phố Vây",
            "pid": 15526,
            "type": 16,
            "region": null,
            "alias": "Phố Vây",
            "is_picked": "",
            "is_delivered": 1,
            "lat": "22.781158",
            "lng": "103.34717750000004"
        },
        {
            "id": 429015,
            "name": "Thà Giàng",
            "pid": 15526,
            "type": 16,
            "region": null,
            "alias": "Thà Giàng",
            "is_picked": "",
            "is_delivered": 1,
            "lat": "22.781158",
            "lng": "103.34717750000004"
        },
        {
            "id": 736288,
            "name": "Thôn Tà Chải",
            "pid": 15526,
            "type": 16,
            "region": null,
            "alias": "thôn Tà Chải",
            "is_picked": "",
            "is_delivered": 1,
            "lat": "22.781158",
            "lng": "103.34717750000004"
        }
    ],
    "log_id": "6758175e74092504"
}