{
    "success": true,
    "message": "Get list address success!",
    "data": [
        {
            "id": 530097,
            "name": "Xóm 1",
            "pid": 20335,
            "type": 18,
            "region": null,
            "alias": "Xóm 1",
            "is_picked": 1,
            "is_delivered": 1,
            "lat": "19.1170669",
            "lng": "105.66178130000003"
        },
        {
            "id": 530107,
            "name": "Xóm 2",
            "pid": 20335,
            "type": 18,
            "region": null,
            "alias": "Xóm 2",
            "is_picked": 1,
            "is_delivered": 1,
            "lat": "19.1170669",
            "lng": "105.66178130000003"
        },
        {
            "id": 530109,
            "name": "Xóm 3",
            "pid": 20335,
            "type": 18,
            "region": null,
            "alias": "Xóm 3",
            "is_picked": 1,
            "is_delivered": 1,
            "lat": "19.1170669",
            "lng": "105.66178130000003"
        },
        {
            "id": 530111,
            "name": "Xóm 4",
            "pid": 20335,
            "type": 18,
            "region": null,
            "alias": "Xóm 4",
            "is_picked": 1,
            "is_delivered": 1,
            "lat": "19.1170669",
            "lng": "105.66178130000003"
        },
        {
            "id": 530113,
            "name": "Xóm 5",
            "pid": 20335,
            "type": 18,
            "region": null,
            "alias": "Xóm 5",
            "is_picked": 1,
            "is_delivered": 1,
            "lat": "19.1170669",
            "lng": "105.66178130000003"
        },
        {
            "id": 530115,
            "name": "Xóm 6",
            "pid": 20335,
            "type": 18,
            "region": null,
            "alias": "Xóm 6",
            "is_picked": 1,
            "is_delivered": 1,
            "lat": "19.1170669",
            "lng": "105.66178130000003"
        },
        {
            "id": 530117,
            "name": "Xóm 7",
            "pid": 20335,
            "type": 18,
            "region": null,
            "alias": "Xóm 7",
            "is_picked": 1,
            "is_delivered": 1,
            "lat": "19.1170669",
            "lng": "105.66178130000003"
        },
        {
            "id": 530119,
            "name": "Xóm 8",
            "pid": 20335,
            "type": 18,
            "region": null,
            "alias": "Xóm 8",
            "is_picked": 1,
            "is_delivered": 1,
            "lat": "19.1170669",
            "lng": "105.66178130000003"
        },
        {
            "id": 530121,
            "name": "Xóm 9",
            "pid": 20335,
            "type": 18,
            "region": null,
            "alias": "Xóm 9",
            "is_picked": 1,
            "is_delivered": 1,
            "lat": "19.1170669",
            "lng": "105.66178130000003"
        },
        {
            "id": 530099,
            "name": "Xóm 10",
            "pid": 20335,
            "type": 18,
            "region": null,
            "alias": "Xóm 10",
            "is_picked": 1,
            "is_delivered": 1,
            "lat": "19.1170669",
            "lng": "105.66178130000003"
        },
        {
            "id": 530101,
            "name": "Xóm 11",
            "pid": 20335,
            "type": 18,
            "region": null,
            "alias": "Xóm 11",
            "is_picked": 1,
            "is_delivered": 1,
            "lat": "19.1170669",
            "lng": "105.66178130000003"
        },
        {
            "id": 530103,
            "name": "Xóm 12",
            "pid": 20335,
            "type": 18,
            "region": null,
            "alias": "Xóm 12",
            "is_picked": 1,
            "is_delivered": 1,
            "lat": "19.1170669",
            "lng": "105.66178130000003"
        },
        {
            "id": 530105,
            "name": "Xóm 13",
            "pid": 20335,
            "type": 18,
            "region": null,
            "alias": "Xóm 13",
            "is_picked": 1,
            "is_delivered": 1,
            "lat": "19.1170669",
            "lng": "105.66178130000003"
        }
    ],
    "log_id": "675812093978f860"
}