{
    "success": true,
    "message": "Get list address success!",
    "data": [
        {
            "id": 626616,
            "name": "Thôn Đăk Phía",
            "pid": 15926,
            "type": 16,
            "region": null,
            "alias": "Thôn Đăk Phía",
            "is_picked": "",
            "is_delivered": 1,
            "lat": "14.4908439",
            "lng": "108.05986600000006"
        },
        {
            "id": 626613,
            "name": "Thôn Kon Bờ Bằn",
            "pid": 15926,
            "type": 16,
            "region": null,
            "alias": "Thôn Kon Bờ Bằn",
            "is_picked": "",
            "is_delivered": 1,
            "lat": "14.4908439",
            "lng": "108.05986600000006"
        },
        {
            "id": 626619,
            "name": "Thôn Kon Braih",
            "pid": 15926,
            "type": 16,
            "region": null,
            "alias": "Thôn Kon Braih",
            "is_picked": "",
            "is_delivered": 1,
            "lat": "14.4908439",
            "lng": "108.05986600000006"
        },
        {
            "id": 626628,
            "name": "Thôn Kon Hơdre",
            "pid": 15926,
            "type": 16,
            "region": null,
            "alias": "Thôn Kon Hơdre",
            "is_picked": "",
            "is_delivered": 1,
            "lat": "14.4908439",
            "lng": "108.05986600000006"
        },
        {
            "id": 626622,
            "name": "Thôn Kon Jong",
            "pid": 15926,
            "type": 16,
            "region": null,
            "alias": "Thôn Kon Jong",
            "is_picked": "",
            "is_delivered": 1,
            "lat": "14.4908439",
            "lng": "108.05986600000006"
        },
        {
            "id": 626625,
            "name": "Thôn Kon Kroc",
            "pid": 15926,
            "type": 16,
            "region": null,
            "alias": "Thôn Kon Kroc",
            "is_picked": "",
            "is_delivered": 1,
            "lat": "14.4908439",
            "lng": "108.05986600000006"
        },
        {
            "id": 626610,
            "name": "Thôn Kon Rôn",
            "pid": 15926,
            "type": 16,
            "region": null,
            "alias": "Thôn Kon rôn",
            "is_picked": "",
            "is_delivered": 1,
            "lat": "14.4908439",
            "lng": "108.05986600000006"
        },
        {
            "id": 626607,
            "name": "Thôn Kon Stiu",
            "pid": 15926,
            "type": 16,
            "region": null,
            "alias": "Thôn Kon Stiu",
            "is_picked": "",
            "is_delivered": 1,
            "lat": "14.4908439",
            "lng": "108.05986600000006"
        }
    ],
    "log_id": "6758174ce02df38"
}